conversations/__about__.py
conversations/__init__.py
conversations/_conversations.py
conversations/config.py
conversations/ai/__init__.py
conversations/ai/_chatgpt.py
conversations/ai/_shorten_transcript.py
conversations/diarise/__init__.py
conversations/diarise/simple/__init__.py
conversations/diarise/simple/_simple.py
conversations/report/__init__.py
conversations/report/_report.py
conversations/report/_text.py
conversations/report/_utils.py
conversations/transcribe/__init__.py
conversations/transcribe/assembly/__init__.py
conversations/transcribe/assembly/_assembly.py
conversations/transcribe/whisper/__init__.py
conversations/transcribe/whisper/_whisper.py
conversations-0.44.0.dist-info/METADATA
conversations-0.44.0.dist-info/WHEEL
conversations-0.44.0.dist-info/licenses/LICENSE.txt
conversations-0.44.0.dist-info/RECORD
