Metadata-Version: 2.4
Name: conversations
Version: 0.44.0
Project-URL: Documentation, https://github.com/rob-luke/conversations#readme
Project-URL: Issues, https://github.com/rob-luke/conversations/issues
Project-URL: Source, https://github.com/rob-luke/conversations
Author-email: Robert Luke <code@robertluke.net>
License-Expression: MIT
License-File: LICENSE.txt
Classifier: Programming Language :: Python
Classifier: Programming Language :: Python :: 3.10
Classifier: Programming Language :: Python :: 3.11
Classifier: Programming Language :: Python :: 3.12
Classifier: Programming Language :: Python :: Implementation :: CPython
Classifier: Programming Language :: Python :: Implementation :: PyPy
Requires-Python: >=3.9
Requires-Dist: assemblyai
Requires-Dist: dominate
Requires-Dist: openai>=1.2.0
Requires-Dist: pooch
Requires-Dist: pydantic-settings>=2.0.0
Requires-Dist: pydantic>=2.0.0
Requires-Dist: tiktoken
Provides-Extra: local
Requires-Dist: openai-whisper; extra == 'local'
Requires-Dist: simple-diarizer; extra == 'local'
Requires-Dist: soundfile; extra == 'local'
Requires-Dist: speechbrain==0.5.13; extra == 'local'
